fedinesia/__init__.py
fedinesia/amnesia.py
fedinesia/config.py
fedinesia/fedi.py
fedinesia/util.py
fedinesia-3.4.14.dist-info/WHEEL
fedinesia-3.4.14.dist-info/entry_points.txt
fedinesia-3.4.14.dist-info/METADATA
fedinesia-3.4.14.dist-info/RECORD
