Metadata-Version: 2.3
Name: fedinesia
Version: 3.4.14
Summary: Deletes old posts from fediverse accounts. Confirmed working with Mastodon, Pleroma (and Forks), Gotosocial, and Takahe
Author: marvin8
Author-email: marvin8 <marvin8@tuta.io>
License: AGPL-3.0-or-later
Classifier: Development Status :: 5 - Production/Stable
Classifier: Environment :: Console
Classifier: Programming Language :: Python
Classifier: Programming Language :: Python :: 3.10
Classifier: Programming Language :: Python :: 3.11
Classifier: Programming Language :: Python :: 3.12
Classifier: Programming Language :: Python :: 3.13
Requires-Dist: h11~=0.16.0
Requires-Dist: h2~=4.3.0
Requires-Dist: httpx~=0.28.1
Requires-Dist: loguru~=0.7.3
Requires-Dist: minimal-activitypub~=1.5.5
Requires-Dist: msgspec~=0.20.0
Requires-Dist: stamina~=25.2.0
Requires-Dist: tomli-w~=1.2.0
Requires-Dist: tomli~=2.4.0
Requires-Dist: tqdm~=4.67.1
Requires-Dist: typer~=0.21.1
Requires-Dist: whenever~=0.9.5
Requires-Python: >=3.10, <3.14
Project-URL: Changelog, https://codeberg.org/marvinsmastodontools/fedinesia/src/branch/main/CHANGELOG.md
Project-URL: Container, https://codeberg.org/marvinsmastodontools/-/packages/container/fedinesia
Project-URL: Documentation, https://codeberg.org/marvinsmastodontools/fedinesia/src/branch/main/README.md
Project-URL: Issues, https://codeberg.org/marvinsmastodontools/fedinesia/issues
Project-URL: Source, https://codeberg.org/marvinsmastodontools/fedinesia
